unicode_stats/__init__.py
unicode_stats/aggregation.py
unicode_stats/config.json
unicode_stats/config.py
unicode_stats/singleton.py
unicode_stats/unicode_parser.py
unicode_stats/cache/unicode_block.json
unicode_stats-0.3.3.dist-info/licenses/LICENSE
unicode_stats-0.3.3.dist-info/METADATA
unicode_stats-0.3.3.dist-info/WHEEL
unicode_stats-0.3.3.dist-info/entry_points.txt
unicode_stats-0.3.3.dist-info/top_level.txt
unicode_stats-0.3.3.dist-info/RECORD
