Metadata-Version: 2.4
Name: unicode_stats
Version: 0.3.3
Summary: Tool to analyze unicode content
Author-email: Adamenko Pavel <padamenko@gmail.com>
License-Expression: MIT
Project-URL: Homepage, https://github.com/padap/unicode_stats
Project-URL: Bug Tracker, https://github.com/padap/unicode_stats/issues
Classifier: Programming Language :: Python :: 3
Classifier: Programming Language :: Python :: 3.6
Classifier: Programming Language :: Python :: 3.7
Classifier: Programming Language :: Python :: 3.8
Classifier: Programming Language :: Python :: 3.9
Classifier: Programming Language :: Python :: 3.10
Classifier: Programming Language :: Python :: 3.11
Classifier: Programming Language :: Python :: 3.12
Requires-Python: >=3.6
License-File: LICENSE
Provides-Extra: dev
Requires-Dist: pytest; extra == "dev"
Requires-Dist: build; extra == "dev"
Dynamic: license-file
